{
    "users": [
        {   
            "id": 1,
            "name": "Iman", 
            "email": "iman@example.com" 
        }
    ],
    "contacts": [
        { 
            "id": 1, 
            "userId": 1, 
            "name": "حمید", 
            "phone": "09123456789" 
        }
    ],
    "banks": [
        { 
            "id": 1,
            "userId": 1,
            "bankName": "Bank Melli", 
            "balance": 1000000 
        }
    ],
    "transactions": [
        {
            "id": 1,
            "userId": 1,
            "bankId": 1,
            "contactId": 1,
            "title": "هدیه",
            "type": "deposit",
            "amount": 200000,
            "description":"",
            "date": "2025-10-29T10:00:00Z"
        }
    ]
}
